MANIFEST.in
README.md
setup.py
extras/mu-autoloader.php
wordpress_cd/__init__.py
wordpress_cd/build.py
wordpress_cd/deploy.py
wordpress_cd/job.py
wordpress_cd/main.py
wordpress_cd/test.py
wordpress_cd.egg-info/PKG-INFO
wordpress_cd.egg-info/SOURCES.txt
wordpress_cd.egg-info/dependency_links.txt
wordpress_cd.egg-info/entry_points.txt
wordpress_cd.egg-info/requires.txt
wordpress_cd.egg-info/top_level.txt
wordpress_cd/datasets/__init__.py
wordpress_cd/datasets/base.py
wordpress_cd/datasets/s3.py
wordpress_cd/drivers/__init__.py
wordpress_cd/drivers/base.py
wordpress_cd/drivers/rsync.py
wordpress_cd/notifications/__init__.py
wordpress_cd/notifications/base.py
wordpress_cd/notifications/discord.py