Metadata-Version: 1.0
Name: wordpress-cd
Version: 0.7.5
Summary: Helper scripts to assist with WordPress-related CI/CD and devops tasks (i.e. build/test/deploy workflows for use with GitLab/Jenkins etc)
Home-page: https://github.com/rossigee/wordpress-cd
Author: Ross Golder
Author-email: ross@golder.org
License: UNKNOWN
Platform: UNKNOWN
